README.txt
setup.py
deepsurv/__init__.py
deepsurv/datasets.py
deepsurv/deep_surv.py
deepsurv/viz.py
deepsurv.egg-info/PKG-INFO
deepsurv.egg-info/SOURCES.txt
deepsurv.egg-info/dependency_links.txt
deepsurv.egg-info/requires.txt
deepsurv.egg-info/top_level.txt