Metadata-Version: 1.1
Name: deepsurv
Version: 0.1.0
Summary: Deep Cox Proportional Hazards Network for deep learning and survival analysis.
Home-page: https://github.com/jaredleekatzman/DeepSurv
Author: Jared Katzman
Author-email: jaredleekatzman@gmail.com
License: MIT
Keywords: survival analysis deep learning cox regression
Platform: UNKNOWN
Classifier: Development Status :: 3 - Alpha
Classifier: Intended Audience :: Developers
Classifier: Intended Audience :: Science/Research
Classifier: Programming Language :: Python
Classifier: Topic :: Scientific/Engineering
